Workbook
Name _: Backend!$M$3:$M$18
Name Customer_First_: Backend!$J$3:$J$6
Name Employees___Learning_: Backend!$L$3:$L$6
Name Finance_: Backend!$I$3:$I$6
Name Internal_processes_: Backend!$K$3:$K$6
Name Slicer_BSC_Focus_area: #N/A
Name Slicer_BSC_Focus_area1: #N/A
Name Slicer_BSC_Perspective: #N/A
Name Slicer_BSC_Perspective1: #N/A
Name Slicer_CSF_Title: #N/A
Name Slicer_CSF_Title1: #N/A
Name Slicer_CSF_Type: #N/A
Name Slicer_CSF_Type1: #N/A
Name Slicer_Responsible: #N/A
Name Slicer_Responsible1: #N/A
Name Table1: Table3[]

Sheet BP Actions
Q2: Color code and definition
Q3: 1 | R3: 1 | S3: Define
Q4: 2 | R4: 2 | S4: Plan
Q5: 3 | R5: 3 | S5: Communicate
Q6: 4 | R6: 4 | S6: Do
Q7: 5 | R7: 5 | S7: Follow-up
B9: BSC | C9: # | D9: BSC Perspective | E9: BSC Focus area | F9: CSF Type | G9: CSF Title | H9: CSF and Actions | I9: Impact | J9: Responsible | K9: Participants | L9: Start | M9: Finish | N9: Comments | O9: Completion rate | Q9: 36 | R9: 37 | S9: 38 | T9: 39 | U9: 40 | V9: 41 | W9: 42 | X9: 43 | Y9: 44 | Z9: 45 | AA9: 46 | AB9: 47 | AC9: 48 | AD9: 49 | AE9: 50 | AF9: 51 | AG9: 52 | AH9: 1 | AI9: 2 | AJ9: 3 | AK9: 4 | AL9: 5 | AM9: 6 | AN9: 7 | AO9: 8 | AP9: 9 | AQ9: 10 | AR9: 11 | AS9: 12 | AT9: 13 | AU9: 14 | AV9: 15 | AW9: 16 | AX9: 17 | AY9: 18 | AZ9: 19 | BA9: 20 | BB9: 21 | BC9: 22 | BD9: 23 | BE9: 24 | BF9: 25 | BG9: 26 | BH9: 27 | BI9: 28 | BJ9: 29 | BK9: 30 | BL9: 31 | BM9: 32 | BN9: 33 | BO9: 34 | BP9: 35
C10: 1 | D10: Finance | E10: Even better cost management | F10: JYSK | G10: Fit for the future | H10: Fit for the future | J10: SSUC
C11: 1.1 | D11: Finance | E11: Even better cost management | F11: JYSK | G11: Fit for the future | H11: Reduce Staff cost | J11: SSUC
C12: 1.1.1 | D12: Finance | E12: Even better cost management | F12: JYSK | G12: Fit for the future | H12: Quarterly optimise number of employees based on turnover | I12: Index productivity (JSI 109,5; JHR 106,9; JBA 109,6; JRS 109,3; JWB 108,7) | J12: SSUC | K12: CD, HOR | L12: W46 | M12: W21 | AA12: 5 | AO12: 5 | BB12: 5
C13: 1.1.2 | D13: Finance | E13: Even better cost management | F13: JYSK | G13: Fit for the future | H13: Refresh staff clothes policy and follow up on ordering and costs | I13: Clothes saving -7.000 eur | J13: SSUC | K13: SCM | L13: W36 | M13: W21 | Q13: 1 | R13: 2 | T13: 4 | AA13: 5 | AO13: 5 | BB13: 5
C14: 1.2 | D14: Finance | E14: Even better cost management | F14: JYSK | G14: Fit for the future | H14: Reduce Premise cost by reducing electricity consumption | I14: Electricity saving -28.000 eur | J14: SSUC
C15: 1.2.1 | D15: Finance | E15: Even better cost management | F15: JYSK | G15: Fit for the future | H15: Define 10% bottom stores in electricity consumption on quarterly base | J15: SSUC | K15: FC, RC | L15: W46 | M15: W21 | AA15: 3 | AO15: 3 | BB15: 3
C16: 1.2.2 | D16: Finance | E16: Even better cost management | F16: JYSK | G16: Fit for the future | H16: Define actions to reduce consumption | J16: SSUC | K16: FC, RC | L16: W47 | M16: W25 | AB16: 4 | AC16: 4 | AD16: 4 | AE16: 4 | AP16: 4 | AQ16: 4 | AR16: 4 | AS16: 4 | BC16: 4 | BD16: 4 | BE16: 4 | BF16: 4
C17: 1.2.3 | D17: Finance | E17: Even better cost management | F17: JYSK | G17: Fit for the future | H17: Quarterly follow up on improvment | J17: SSUC | K17: FC, RC | L17: W46 | M17: W21 | AA17: 5 | AO17: 5 | BB17: 5
C18: 1.3 | D18: Finance | E18: Even better cost management | F18: JYSK | G18: Fit for the future | H18: Reduce Premise cost by reducing waste costs | I18: Waste saving -19.000 | J18: SSUC
C19: 1.3.1 | D19: Finance | E19: Even better cost management | F19: JYSK | G19: Fit for the future | H19: Choose one bottom store per district and analyze consumption | J19: SSUC | K19: RC | L19: W46 | M19: W21 | AA19: 3 | AO19: 3 | BB19: 3
C20: 1.3.2 | D20: Finance | E20: Even better cost management | F20: JYSK | G20: Fit for the future | H20: Define actions to reduce consumption | J20: SSUC | L20: W47 | M20: W25 | AB20: 4 | AC20: 4 | AD20: 4 | AE20: 4 | AP20: 4 | AQ20: 4 | AR20: 4 | AS20: 4 | BC20: 4 | BD20: 4 | BE20: 4 | BF20: 4
C21: 1.3.3 | D21: Finance | E21: Even better cost management | F21: JYSK | G21: Fit for the future | H21: Quarterly follow up on improvment | J21: SSUC | K21: FC, RC | L21: W46 | M21: W21 | AA21: 5 | AO21: 5 | BB21: 5
C22: 1.4 | D22: Finance | E22: Even better cost management | F22: JYSK | G22: Fit for the future | H22: Reduce Premise cost by focusing on maintenance costs | I22: Maintenance saving -22.000 | J22: SSUC
C23: 1.4.1 | D23: Finance | E23: Even better cost management | F23: JYSK | G23: Fit for the future | H23: Analyse number of regular store visits and supplier conditions | J23: SSUC | L23: W35 | M23: W38 | P23: 1 | Q23: 2
C24: 1.4.2 | D24: Finance | E24: Even better cost management | F24: JYSK | G24: Fit for the future | H24: Prepare actions according to findings from analyse | J24: SSUC | K24: OA | L24: W35 | M24: W38 | R24: 4
C25: 1.5 | D25: Finance | E25: Even better cost management | F25: JYSK | G25: Fit for the future | H25: Reduce administrative cost | I25: Stationary saving -25.000 | J25: SSUC
C26: 1.5.1 | D26: Finance | E26: Even better cost management | F26: JYSK | G26: Fit for the future | H26: Prepare guideline for new office supplies supplier | J26: SSUC | K26: OA | L26: W36 | M26: W38 | P26: 1 | Q26: 2 | S26: 3
C27: 1.5.2 | D27: Finance | E27: Even better cost management | F27: JYSK | G27: Fit for the future | H27: Send to DM's consumption of office supplies by stores and follow up on quarterly base | J27: SSUC | K27: RC | L27: W39 | M27: W21 | T27: 5 | AA27: 5 | AO27: 5 | BB27: 5
C28: 1.6 | D28: Finance | E28: Even better cost management | F28: JYSK | G28: Fit for the future | H28: Reduce investment costs | I28: Investment savings - 50.000 eur | J28: SSUC
C29: 1.6.1 | D29: Finance | E29: Even better cost management | F29: JYSK | G29: Fit for the future | H29: Put additional focus on investement costs by regulary benchmark of external supplier prices | J29: SSUC | L29: W39 | M29: W24 | T29: 4 | V29: 4 | AA29: 4 | AE29: 4 | AJ29: 4 | AO29: 4 | AS29: 4 | AW29: 4 | BB29: 4 | BE29: 4
C30: 2 | D30: Internal processes | E30: Attractive stores | F30: JYSK | G30: Optimise Retail Operations | H30: Optimise Retail Operations | I30: Index productivity (JSI 109,5; JHR 106,9; JBA 109,6; JRS 109,3; JWB 108,7) | J30: DEL
C31: 2.1 | D31: Internal processes | E31: Attractive stores | F31: JYSK | G31: Optimise Retail Operations | H31: Implement new goals setup | J31: DEL
C32: 2.1.1 | D32: Internal processes | E32: Attractive stores | F32: JYSK | G32: Optimise Retail Operations | H32: Prepare training/communication materials for new goals/KPI setup | J32: DEL | K32: RC, DM, SM | L32: W35 | M32: W36 | P32: 1 | Q32: 2
C33: 2.1.2 | D33: Internal processes | E33: Attractive stores | F33: JYSK | G33: Optimise Retail Operations | H33: Present and train DMs (National Retail Meeting) and SMs (Country SM meeting) | J33: DEL | K33: RC, DM, SM | L33: W37 | M33: W39 | R33: 4 | T33: 4
C34: 2.1.3 | D34: Internal processes | E34: Attractive stores | F34: JYSK | G34: Optimise Retail Operations | H34: SMs present and train all store staff | J34: DEL | K34: RC, DM, SM | L34: W40 | M34: W44 | U34: 4 | V34: 4 | W34: 4 | X34: 4 | Y34: 4
C35: 2.1.4 | D35: Internal processes | E35: Attractive stores | F35: JYSK | G35: Optimise Retail Operations | H35: DMs follow up on understanding during GSM days | J35: DEL | K35: RC, DM, SM | L35: W45 | M35: W18 | Z35: 5 | AA35: 5 | AB35: 5 | AC35: 5 | AD35: 5 | AE35: 5 | AF35: 5 | AG35: 5 | AH35: 5 | AI35: 5 | AJ35: 5 | AK35: 5 | AL35: 5 | AM35: 5 | AN35: 5 | AO35: 5 | AP35: 5 | AQ35: 5 | AR35: 5 | AS35: 5 | AT35: 5 | AU35: 5 | AV35: 5 | AW35: 5 | AX35: 5 | AY35: 5
C36: 2.2 | D36: Internal processes | E36: Attractive stores | F36: JYSK | G36: Optimise Retail Operations | H36: Optimise store communication | J36: DEL
C37: 2.2.1 | D37: Internal processes | E37: Attractive stores | F37: JYSK | G37: Optimise Retail Operations | H37: Define 1 store communication ambassador (RM) per country and describe the new role | J37: DEL | K37: RM, DM | L37: W35 | M37: W36 | P37: 1 | Q37: 2
C38: 2.2.2 | D38: Internal processes | E38: Attractive stores | F38: JYSK | G38: Optimise Retail Operations | H38: Present new role to admin users and train them in correct usage of all communication channels | J38: DEL | K38: RM, DM | L38: W38 | M38: W38 | R38: 3
C39: 2.2.3 | D39: Internal processes | E39: Attractive stores | F39: JYSK | G39: Optimise Retail Operations | H39: Store communication ambassador analyse once per quarter all communication to the stores | J39: DEL | K39: RM, DM | L39: W45 | M39: W32 | Z39: 5 | AO39: 5 | BB39: 5 | BM39: 5
C40: 2.2.4 | D40: Internal processes | E40: Attractive stores | F40: JYSK | G40: Optimise Retail Operations | H40: Present results to admin users and refresh knowledge about communication to the stores | J40: DEL | K40: RM, DM | L40: W45 | M40: W32 | Z40: 3 | AO40: 3 | BB40: 3 | BM40: 3
C41: 2.3 | D41: Internal processes | E41: Attractive stores | F41: JYSK | G41: Optimise Retail Operations | H41: Minimise locally implemented procedures | J41: DEL
C42: 2.3.1 | D42: Internal processes | E42: Attractive stores | F42: JYSK | G42: Optimise Retail Operations | H42: Create list of all locally implemented procedures | J42: DEL | K42: RSS, DM, IA | L42: W35 | M42: W35 | P42: 1
C43: 2.3.2 | D43: Internal processes | E43: Attractive stores | F43: JYSK | G43: Optimise Retail Operations | H43: Go through all and define which can be removed and how to improve locally implemented procedures which needs to stay | J43: DEL | K43: RSS, DM, IA | L43: W36 | M43: W36 | Q43: 2
C44: 2.3.3 | D44: Internal processes | E44: Attractive stores | F44: JYSK | G44: Optimise Retail Operations | H44: Communicate and train on SM meetings in district | J44: DEL | K44: RSS, DM, IA | L44: W37 | M44: W39 | R44: 4 | T44: 4
C45: 2.3.4 | D45: Internal processes | E45: Attractive stores | F45: JYSK | G45: Optimise Retail Operations | H45: DM follow up during AS (local focus area) on implementation | J45: DEL | K45: RSS, DM, IA | L45: W52 | M45: W12 | AG45: 5 | AH45: 5 | AI45: 5 | AP45: 5 | AQ45: 5 | AR45: 5 | AS45: 5
C46: 3 | D46: Employees & learning | E46: Attractive place to work | F46: JYSK | G46: Attract the future | H46: Attract the future | J46: JCU
C47: 3.1 | D47: Employees & learning | E47: Attractive place to work | F47: JYSK | G47: Attract the future | H47: Improve communication of benefits internally and externally | I47: STO total (JSI/JBA/JRS < 20; JHR < 15) | J47: JCU
C48: 3.1.1 | D48: Employees & learning | E48: Attractive place to work | F48: JYSK | G48: Attract the future | H48: Define list of relevant benefits per country and prepare communication plan with country specific defined channels | J48: JCU | K48: HR | L48: W40 | M48: W42 | U48: 1 | V48: 2 | W48: 3
C49: 3.1.2 | D49: Employees & learning | E49: Attractive place to work | F49: JYSK | G49: Attract the future | H49: Adjust job ads and storytelling for better benefit communication/visibility | J49: JCU | K49: HRBP's, ComM | L49: W45 | M49: W45 | Z49: 4
C50: 3.1.3 | D50: Employees & learning | E50: Attractive place to work | F50: JYSK | G50: Attract the future | H50: Monthly evaluate number of applicants and quality according to rating in SmartRecruiters and adjust communication accordingly | J50: JCU | K50: HRBP's | L50: W45 | M50: W27 | Z50: 5 | AD50: 5 | AH50: 5 | AM50: 5 | AQ50: 5 | AU50: 5 | AZ50: 5 | BD50: 5 | BH50: 5
C51: 3.1.4 | D51: Employees & learning | E51: Attractive place to work | F51: JYSK | G51: Attract the future | H51: Quarterly follow up on CMT | J51: JCU | K51: HRM | L51: W49 | M51: W24 | AD51: 5 | AS51: 5 | BE51: 5
C52: 3.2 | D52: Employees & learning | E52: Attractive place to work | F52: JYSK | G52: Attract the future | H52: Secure quality of recruitment process | I52: STO new employees (JSI/JRS < 25; JHR/JBA < 20) | J52: JCU
C53: 3.2.1 | D53: Employees & learning | E53: Attractive place to work | F53: JYSK | G53: Attract the future | H53: Increase focus on preffered profile, critical job factors and potential by DM/HRBP challenge every new employment and internal promotion | J53: JCU | K53: HRBP's, RM's, DM's | L53: W35 | M53: W37 | P53: 1 | Q53: 2 | R53: 3
C54: 3.2.2 | D54: Employees & learning | E54: Attractive place to work | F54: JYSK | G54: Attract the future | H54: Relaunch refferal program on SM meeting and HO kick off to increase quality of candidates and engagement of employees | J54: JCU | K54: HRM | L54: W37 | M54: W39 | R54: 4 | T54: 4
C55: 3.2.3 | D55: Employees & learning | E55: Attractive place to work | F55: JYSK | G55: Attract the future | H55: Monthly present and discuss profiles of new employees and internal promotions on MRM | J55: JCU | K55: HRBP's. RM's | L55: W41 | M55: W27 | V55: 5 | Z55: 5 | AE55: 5 | AJ55: 5 | AM55: 5 | AQ55: 5 | AV55: 5 | AZ55: 5 | BD55: 5 | BH55: 5
C56: 3.2.4 | D56: Employees & learning | E56: Attractive place to work | F56: JYSK | G56: Attract the future | H56: Non preferred profile employement/promotions must be approved by HRM/HOR | J56: JCU | K56: HRBP's. RM's | L56: W37 | M56: W35
C57: 3.3.5 | D57: Employees & learning | E57: Attractive place to work | F57: JYSK | G57: Attract the future | H57: Quarterly follow up on preffered profiles on CMT | J57: JCU | K57: HRM | L57: W49 | M57: W24 | AD57: 5 | AS57: 5 | BE57: 5
C58: 3.3 | D58: Employees & learning | E58: Attractive place to work | F58: JYSK | G58: Attract the future | H58: Build Influencer Team to secure strong engagement | I58: TTH < 30 | J58: JCU
C59: 3.3.1 | D59: Employees & learning | E59: Attractive place to work | F59: JYSK | G59: Attract the future | H59: Define selection process of influencers, level of involvement and goals of the team | J59: JCU | K59: ComM, HR | L59: W35 | M59: W39 | P59: 1 | Q59: 2 | R59: 3 | T59: 3
C60: 3.3.2 | D60: Employees & learning | E60: Attractive place to work | F60: JYSK | G60: Attract the future | H60: Train Influencer Team and align cross country on targets and channels | J60: JCU | K60: ComM, HR | L60: W41 | M60: W41 | V60: 4
C61: 3.3.3 | D61: Employees & learning | E61: Attractive place to work | F61: JYSK | G61: Attract the future | H61: Quarterly organize planning meetings for Influencer Team with tasks, goals and planned projects and campaigns | J61: JCU | K61: ComM, HR | L61: W4 | M61: W14 | AK61: 4 | AU61: 4
C62: 3.3.4 | D62: Employees & learning | E62: Attractive place to work | F62: JYSK | G62: Attract the future | H62: Quarterly evaluate campaign success and KPI's and adjust actions in EB calendar | J62: JCU | K62: ComM, HR | L62: W49 | M62: W24 | AD62: 5 | AS62: 5 | BE62: 5
C63: 4 | D63: Employees & learning | E63: Attractive place to work | F63: JYSK | G63: Retain and empower our talent and performers | H63: Retain and empower our talent and performers | J63: JCU
C64: 4.1 | D64: Employees & learning | E64: Attractive place to work | F64: JYSK | G64: Retain and empower our talent and performers | H64: Roll out of new Learning Management System and Performance Managment system | I64: STO DepSM (JSI/JBA/JRS < 20; JHR < 15) | J64: JCU
C65: 4.1.1 | D65: Employees & learning | E65: Attractive place to work | F65: JYSK | G65: Retain and empower our talent and performers | H65: Prepare roll out plan and communicate on NRM and SM meeting | J65: JCU | K65: HRM | L65: W35 | M65: W39 | P65: 1 | Q65: 2 | R65: 3 | T65: 3
C66: 4.1.2 | D66: Employees & learning | E66: Attractive place to work | F66: JYSK | G66: Retain and empower our talent and performers | H66: HR train DM's on MRM | J66: JCU | K66: HRBP's | L66: W3 | M66: W3 | AJ66: 4
C67: 4.1.3 | D67: Employees & learning | E67: Attractive place to work | F67: JYSK | G67: Retain and empower our talent and performers | H67: DM's train SM's | J67: JCU | K67: DM's | L67: W4 | M67: W5 | AK67: 4 | AL67: 4
C68: 4.1.4 | D68: Employees & learning | E68: Attractive place to work | F68: JYSK | G68: Retain and empower our talent and performers | H68: Follow up on roll out and implementation by HRBP's and DM's in Q3 and Q4 | J68: JCU | K68: HRBP's, DM's | L68: W9 | M68: W35 | AS68: 5 | BE68: 5
C69: 4.2 | D69: Employees & learning | E69: Attractive place to work | F69: JYSK | G69: Retain and empower our talent and performers | H69: Improve new employee Onboarding process | I69: STO new employees (JSI/JRS < 25; JHR/JBA < 20) | J69: JCU
C70: 4.2.1 | D70: Employees & learning | E70: Attractive place to work | F70: JYSK | G70: Retain and empower our talent and performers | H70: Secure follow up on onboarding process by DM/HRBP/RM during 3 AS rounds, DM/HRBP operational days and RM/HRBP operational days | J70: JCU | K70: HRBP's, DM's, RM's | N70: Define local AS rounds (IPR)
C71: 4.2.2 | D71: Employees & learning | E71: Attractive place to work | F71: JYSK | G71: Retain and empower our talent and performers | H71: Quarterly present onboarding survey results on MRM and define actions | J71: JCU | K71: HRBP's, DM's | L71: W41 | M71: W19 | V71: 5 | AE71: 5 | AQ71: 5 | AZ71: 5
C72: 4.2.3 | D72: Employees & learning | E72: Attractive place to work | F72: JYSK | G72: Retain and empower our talent and performers | H72: Twice a year HoR and HRM follow up on onboarding process OTR with prepared check list and survey results | J72: JCU | K72: HoR, HRM | L72: W59 | M72: W10 | AE72: 4 | AQ72: 4
C73: 4.2.4 | D73: Employees & learning | E73: Attractive place to work | F73: JYSK | G73: Retain and empower our talent and performers | H73: Quarterly follow up on CMT | J73: JCU | K73: HRM | L73: W49 | M73: W24 | AD73: 5 | AS73: 5 | BE73: 5
C74: 4.3 | D74: Employees & learning | E74: Attractive place to work | F74: JYSK | G74: Retain and empower our talent and performers | H74: Improve mentoring and follow up of Talents and SMT's | I74: IFR SM > 80; IFR DepSM > 70 | J74: JCU
C75: 4.3.1 | D75: Employees & learning | E75: Attractive place to work | F75: JYSK | G75: Retain and empower our talent and performers | H75: Organize twice a year WS with mentors for Talents and twice a year WS with mentors for SMT's to align on process and quality of mentoring | J75: JCU | K75: HRBP, DM | L75: W41 | M75: W14 | V75: 1 | W75: 2 | X75: 3 | Y75: 4 | AG75: 1 | AH75: 2 | AI75: 3 | AJ75: 4 | AM75: 4 | AR75: 1 | AS75: 2 | AT75: 3 | AU75: 4
C76: 4.3.2 | D76: Employees & learning | E76: Attractive place to work | F76: JYSK | G76: Retain and empower our talent and performers | H76: On MRM present status of Talents and SMT's after 1st modul of Talent programe and each modul of SMT programe | J76: JCU | K76: HRBP, RM | L76: W45 | M76: W24 | Z76: 5 | AM76: 5 | AV76: 5 | BD76: 5
C77: 4.3.3 | D77: Employees & learning | E77: Attractive place to work | F77: JYSK | G77: Retain and empower our talent and performers | H77: Twice a year HoR and HRM follow up on talents and SMT's OTR with prepared overview | J77: JCU | K77: HoR, HRM | L77: W50 | M77: W10 | AE77: 4 | AQ77: 4
C78: 4.3.4 | D78: Employees & learning | E78: Attractive place to work | F78: JYSK | G78: Retain and empower our talent and performers | H78: Quarterly follow up on CMT | J78: JCU | K78: HRM | L78: W49 | M78: W24 | AD78: 5 | AS78: 5 | BE78: 5
C79: 4.4 | D79: Employees & learning | E79: Attractive place to work | F79: JYSK | G79: Retain and empower our talent and performers | H79: Secure IO fulfilment and quality | I79: STO DepSM (JSI/JBA/JRS < 20; JHR < 15) | J79: JCU
C80: 4.4.1 | D80: Employees & learning | E80: Attractive place to work | F80: JYSK | G80: Retain and empower our talent and performers | H80: Present current status of IO fulfilment and percentage of preffered profiles on NRM and SM meeting in September to show reality check and secure focus | J80: JCU | K80: HoR, HRM | L80: W35 | M80: W39 | P80: 1 | Q80: 2 | R80: 3 | T80: 3
C81: 4.4.2 | D81: Employees & learning | E81: Attractive place to work | F81: JYSK | G81: Retain and empower our talent and performers | H81: Monthly on MRM and MCRM present IO fullfilment and preffered profiles of employees on all levels | J81: JCU | K81: HRBP's, HoR | L81: W40 | M81: W27 | U81: 5 | V81: 5 | Z81: 5 | AD81: 5 | AE81: 5 | AI81: 5 | AJ81: 5 | AL81: 5 | AM81: 5 | AQ81: 5 | AU81: 5 | AV81: 5 | AZ81: 5 | BD81: 5 | BH81: 5
C82: 4.4.3 | D82: Employees & learning | E82: Attractive place to work | F82: JYSK | G82: Retain and empower our talent and performers | H82: Prepare actions for IO fulfilment and prefferred profile status according to results | J82: JCU | K82: DM's, HRBP's | L82: W41 | M82: W27 | V82: 4 | Z82: 4 | AE82: 4 | AJ82: 4 | AM82: 4 | AQ82: 4 | AV82: 4 | AZ82: 4 | BD82: 4 | BH82: 4
C83: 4.4.4 | D83: Employees & learning | E83: Attractive place to work | F83: JYSK | G83: Retain and empower our talent and performers | H83: Quarterly follow up on CMT and every second month HoR and HRM | J83: JCU | K83: HRM, HoR | L83: W49 | M83: W24 | AD83: 5 | AS83: 5 | BE83: 5
C84: 4.5 | D84: Employees & learning | E84: Attractive place to work | F84: JYSK | G84: Retain and empower our talent and performers | H84: Launch wellbeing program for employees | I84: STO total (JSI/JBA/JRS < 20; JHR < 15) | J84: JCU
C85: 4.5.1 | D85: Employees & learning | E85: Attractive place to work | F85: JYSK | G85: Retain and empower our talent and performers | H85: Define topics and yearly wellbeing calendar - 5 months per FY we'll have wellbeing topic (How to eat healthy at work, How to deal with stress, financial literacy, Benefits of regular excersize ...) During those months we'll organize webinars on defined topis for all employees and post blogs and vlogs intenally. | J85: JCU | K85: HR | L85: W35 | M85: W39 | P85: 1 | Q85: 2 | R85: 3 | T85: 3
C86: 4.5.2 | D86: Employees & learning | E86: Attractive place to work | F86: JYSK | G86: Retain and empower our talent and performers | H86: Prepare communication plan: internally to promote wellbeing program and announce webinars and externally to promote additional benefits of working in JYSK | J86: JCU | K86: HR, ComM | L86: W38 | M86: W39 | R86: 4 | T86: 4
C87: 4.5.3 | D87: Employees & learning | E87: Attractive place to work | F87: JYSK | G87: Retain and empower our talent and performers | H87: Prepare landing page for wellbeing materials for employees and promotional materials for external communication | J87: JCU | K87: ComM, HR | L87: W37 | M87: W37 | R87: 4
C88: 4.5.4 | D88: Employees & learning | E88: Attractive place to work | F88: JYSK | G88: Retain and empower our talent and performers | H88: Follow up on execution and adapt plan and communication | J88: JCU | K88: HR | L88: W49 | M88: W24 | AD88: 5 | AS88: 5 | BE88: 5
C89: 5 | D89: Finance | E89: Sales growth | F89: Service function | G89: Explore, implement and leverage Artificial Intelligence | H89: Explore, implement and leverage Artificial Intelligence
C90: 5.1 | D90: Finance | E90: Sales growth | F90: Service Function | G90: Explore, implement and leverage Artificial Intelligence | H90: Action
C91: 5.1.1 | D91: Finance | E91: Sales growth | F91: Service Function | G91: Explore, implement and leverage Artificial Intelligence | H91: Sub-action
C92: 5.2 | D92: Finance | E92: Sales growth | F92: Service Function | G92: Explore, implement and leverage Artificial Intelligence | H92: Action
C93: 6 | D93: Finance | E93: Sales growth | F93: Service function | G93: Secure the voice of the customer through insights | H93: Secure the voice of the customer through insights
C94: 6.1 | D94: Finance | E94: Sales growth | F94: Service Function | G94: Secure the voice of the customer through insights | H94: Action
C95: 6.1.1 | D95: Finance | E95: Sales growth | F95: Service Function | G95: Secure the voice of the customer through insights | H95: Sub-action
C96: 6.2 | D96: Finance | E96: Sales growth | F96: Service Function | G96: Secure the voice of the customer through insights | H96: Action
C97: 7 | D97: Finance | E97: Sales growth | F97: Service function | G97: Make JYSK more sustainable | H97: Make JYSK more sustainable
C98: 7.1 | D98: Finance | E98: Sales growth | F98: Service Function | G98: Make JYSK more sustainable | H98: Action
C99: 7.1.1 | D99: Finance | E99: Sales growth | F99: Service Function | G99: Make JYSK more sustainable | H99: Sub-action
C100: 7.2 | D100: Finance | E100: Sales growth | F100: Service Function | G100: Make JYSK more sustainable | H100: Action
C101: 8 | D101: Finance | E101: Sales growth | F101: Service function | G101: Enhance benefits from RTM | H101: Enhance benefits from RTM
C102: 8.1 | D102: Finance | E102: Sales growth | F102: Service Function | G102: Enhance benefits from RTM | H102: Action
...

Sheet High-level overview
C9: 3 | D9: 5 | E9: 2 | F9: 3 | G9: 4 | H9: 6 | I9: 8 | J9: 10 | K9: 11 | L9: 12 | M9: 13
C10: Updated automatically from BP Actions sheet - do not change
B11: BSC | C11: # | D11: CSF Title | E11: BSC Perspective | F11: BSC Focus area | G11: CSF Type | H11: CSF or Action | I11: Responsible | J11: Start | K11: Finish | L11: Comments | M11: Completion rate
C12: 1 | D12: =IFERROR(IF(VLOOKUP(Table2[[#This Row],['#]],Table3[['#]:[Completion rate]],'High-level overview'!D$9,FALSE)=0,"",VLOOKUP(Table2[[#This Row],['#]],Table3[['#]:[Completion rate]],'High-level overview'!D$9,FALSE)),"") -> Fit for the future | E12: =IFERROR(IF(VLOOKUP(Table2[[#This Row],['#]],Table3[['#]:[Completion rate]],'High-level overview'!E$9,FALSE)=0,"",VLOOKUP(Table2[[#This Row],['#]],Table3[['#]:[Completion rate]],'High-level overview'!E$9,FALSE)),"") -> Finance | F12: =IFERROR(IF(VLOOKUP(Table2[[#This Row],['#]],Table3[['#]:[Completion rate]],'High-level overview'!F$9,FALSE)=0,"",VLOOKUP(Table2[[#This Row],['#]],Table3[['#]:[Completion rate]],'High-level overview'!F$9,FALSE)),"") -> Even better cost management | G12: =IFERROR(IF(VLOOKUP(Table2[[#This Row],['#]],Table3[['#]:[Completion rate]],'High-level overview'!G$9,FALSE)=0,"",VLOOKUP(Table2[[#This Row],['#]],Table3[['#]:[Completion rate]],'High-level overview'!G$9,FALSE)),"") -> JYSK | H12: =IFERROR(IF(VLOOKUP(Table2[[#This Row],['#]],Table3[['#]:[Completion rate]],'High-level overview'!H$9,FALSE)=0,"",VLOOKUP(Table2[[#This Row],['#]],Table3[['#]:[Completion rate]],'High-level overview'!H$9,FALSE)),"") -> Fit for the future | I12: =IFERROR(IF(VLOOKUP(Table2[[#This Row],['#]],Table3[['#]:[Completion rate]],'High-level overview'!I$9,FALSE)=0,"",VLOOKUP(Table2[[#This Row],['#]],Table3[['#]:[Completion rate]],'High-level overview'!I$9,FALSE)),"") -> SSUC | J12: =IFERROR(IF(VLOOKUP(Table2[[#This Row],['#]],Table3[['#]:[Completion rate]],'High-level overview'!J$9,FALSE)=0,"",VLOOKUP(Table2[[#This Row],['#]],Table3[['#]:[Completion rate]],'High-level overview'!J$9,FALSE)),"") | K12: =IFERROR(IF(VLOOKUP(Table2[[#This Row],['#]],Table3[['#]:[Completion rate]],'High-level overview'!K$9,FALSE)=0,"",VLOOKUP(Table2[[#This Row],['#]],Table3[['#]:[Completion rate]],'High-level overview'!K$9,FALSE)),"") | ... M12: =IFERROR(IF(VLOOKUP(Table2[[#This Row],['#]],Table3[['#]:[Completion rate]],'High-level overview'!M$9,FALSE)=0,"",VLOOKUP(Table2[[#This Row],['#]],Table3[['#]:[Completion rate]],'High-level overview'!M$9,FALSE)),"")
C13: 2 | D13: =IFERROR(IF(VLOOKUP(Table2[[#This Row],['#]],Table3[['#]:[Completion rate]],'High-level overview'!D$9,FALSE)=0,"",VLOOKUP(Table2[[#This Row],['#]],Table3[['#]:[Completion rate]],'High-level overview'!D$9,FALSE)),"") -> Optimise Retail Operations | E13: =IFERROR(IF(VLOOKUP(Table2[[#This Row],['#]],Table3[['#]:[Completion rate]],'High-level overview'!E$9,FALSE)=0,"",VLOOKUP(Table2[[#This Row],['#]],Table3[['#]:[Completion rate]],'High-level overview'!E$9,FALSE)),"") -> Internal processes | F13: =IFERROR(IF(VLOOKUP(Table2[[#This Row],['#]],Table3[['#]:[Completion rate]],'High-level overview'!F$9,FALSE)=0,"",VLOOKUP(Table2[[#This Row],['#]],Table3[['#]:[Completion rate]],'High-level overview'!F$9,FALSE)),"") -> Attractive stores | G13: =IFERROR(IF(VLOOKUP(Table2[[#This Row],['#]],Table3[['#]:[Completion rate]],'High-level overview'!G$9,FALSE)=0,"",VLOOKUP(Table2[[#This Row],['#]],Table3[['#]:[Completion rate]],'High-level overview'!G$9,FALSE)),"") -> JYSK | H13: =IFERROR(IF(VLOOKUP(Table2[[#This Row],['#]],Table3[['#]:[Completion rate]],'High-level overview'!H$9,FALSE)=0,"",VLOOKUP(Table2[[#This Row],['#]],Table3[['#]:[Completion rate]],'High-level overview'!H$9,FALSE)),"") -> Optimise Retail Operations | I13: =IFERROR(IF(VLOOKUP(Table2[[#This Row],['#]],Table3[['#]:[Completion rate]],'High-level overview'!I$9,FALSE)=0,"",VLOOKUP(Table2[[#This Row],['#]],Table3[['#]:[Completion rate]],'High-level overview'!I$9,FALSE)),"") -> DEL | J13: =IFERROR(IF(VLOOKUP(Table2[[#This Row],['#]],Table3[['#]:[Completion rate]],'High-level overview'!J$9,FALSE)=0,"",VLOOKUP(Table2[[#This Row],['#]],Table3[['#]:[Completion rate]],'High-level overview'!J$9,FALSE)),"") | K13: =IFERROR(IF(VLOOKUP(Table2[[#This Row],['#]],Table3[['#]:[Completion rate]],'High-level overview'!K$9,FALSE)=0,"",VLOOKUP(Table2[[#This Row],['#]],Table3[['#]:[Completion rate]],'High-level overview'!K$9,FALSE)),"") | ... M13: =IFERROR(IF(VLOOKUP(Table2[[#This Row],['#]],Table3[['#]:[Completion rate]],'High-level overview'!M$9,FALSE)=0,"",VLOOKUP(Table2[[#This Row],['#]],Table3[['#]:[Completion rate]],'High-level overview'!M$9,FALSE)),"")
C14: 3 | D14: =IFERROR(IF(VLOOKUP(Table2[[#This Row],['#]],Table3[['#]:[Completion rate]],'High-level overview'!D$9,FALSE)=0,"",VLOOKUP(Table2[[#This Row],['#]],Table3[['#]:[Completion rate]],'High-level overview'!D$9,FALSE)),"") -> Attract the future | E14: =IFERROR(IF(VLOOKUP(Table2[[#This Row],['#]],Table3[['#]:[Completion rate]],'High-level overview'!E$9,FALSE)=0,"",VLOOKUP(Table2[[#This Row],['#]],Table3[['#]:[Completion rate]],'High-level overview'!E$9,FALSE)),"") -> Employees & learning | F14: =IFERROR(IF(VLOOKUP(Table2[[#This Row],['#]],Table3[['#]:[Completion rate]],'High-level overview'!F$9,FALSE)=0,"",VLOOKUP(Table2[[#This Row],['#]],Table3[['#]:[Completion rate]],'High-level overview'!F$9,FALSE)),"") -> Attractive place to work | G14: =IFERROR(IF(VLOOKUP(Table2[[#This Row],['#]],Table3[['#]:[Completion rate]],'High-level overview'!G$9,FALSE)=0,"",VLOOKUP(Table2[[#This Row],['#]],Table3[['#]:[Completion rate]],'High-level overview'!G$9,FALSE)),"") -> JYSK | H14: =IFERROR(IF(VLOOKUP(Table2[[#This Row],['#]],Table3[['#]:[Completion rate]],'High-level overview'!H$9,FALSE)=0,"",VLOOKUP(Table2[[#This Row],['#]],Table3[['#]:[Completion rate]],'High-level overview'!H$9,FALSE)),"") -> Attract the future | I14: =IFERROR(IF(VLOOKUP(Table2[[#This Row],['#]],Table3[['#]:[Completion rate]],'High-level overview'!I$9,FALSE)=0,"",VLOOKUP(Table2[[#This Row],['#]],Table3[['#]:[Completion rate]],'High-level overview'!I$9,FALSE)),"") -> JCU | J14: =IFERROR(IF(VLOOKUP(Table2[[#This Row],['#]],Table3[['#]:[Completion rate]],'High-level overview'!J$9,FALSE)=0,"",VLOOKUP(Table2[[#This Row],['#]],Table3[['#]:[Completion rate]],'High-level overview'!J$9,FALSE)),"") | K14: =IFERROR(IF(VLOOKUP(Table2[[#This Row],['#]],Table3[['#]:[Completion rate]],'High-level overview'!K$9,FALSE)=0,"",VLOOKUP(Table2[[#This Row],['#]],Table3[['#]:[Completion rate]],'High-level overview'!K$9,FALSE)),"") | ... M14: =IFERROR(IF(VLOOKUP(Table2[[#This Row],['#]],Table3[['#]:[Completion rate]],'High-level overview'!M$9,FALSE)=0,"",VLOOKUP(Table2[[#This Row],['#]],Table3[['#]:[Completion rate]],'High-level overview'!M$9,FALSE)),"")
C15: 4 | D15: =IFERROR(IF(VLOOKUP(Table2[[#This Row],['#]],Table3[['#]:[Completion rate]],'High-level overview'!D$9,FALSE)=0,"",VLOOKUP(Table2[[#This Row],['#]],Table3[['#]:[Completion rate]],'High-level overview'!D$9,FALSE)),"") -> Retain and empower our talent and performers | E15: =IFERROR(IF(VLOOKUP(Table2[[#This Row],['#]],Table3[['#]:[Completion rate]],'High-level overview'!E$9,FALSE)=0,"",VLOOKUP(Table2[[#This Row],['#]],Table3[['#]:[Completion rate]],'High-level overview'!E$9,FALSE)),"") -> Employees & learning | F15: =IFERROR(IF(VLOOKUP(Table2[[#This Row],['#]],Table3[['#]:[Completion rate]],'High-level overview'!F$9,FALSE)=0,"",VLOOKUP(Table2[[#This Row],['#]],Table3[['#]:[Completion rate]],'High-level overview'!F$9,FALSE)),"") -> Attractive place to work | G15: =IFERROR(IF(VLOOKUP(Table2[[#This Row],['#]],Table3[['#]:[Completion rate]],'High-level overview'!G$9,FALSE)=0,"",VLOOKUP(Table2[[#This Row],['#]],Table3[['#]:[Completion rate]],'High-level overview'!G$9,FALSE)),"") -> JYSK | H15: =IFERROR(IF(VLOOKUP(Table2[[#This Row],['#]],Table3[['#]:[Completion rate]],'High-level overview'!H$9,FALSE)=0,"",VLOOKUP(Table2[[#This Row],['#]],Table3[['#]:[Completion rate]],'High-level overview'!H$9,FALSE)),"") -> Retain and empower our talent and performers | I15: =IFERROR(IF(VLOOKUP(Table2[[#This Row],['#]],Table3[['#]:[Completion rate]],'High-level overview'!I$9,FALSE)=0,"",VLOOKUP(Table2[[#This Row],['#]],Table3[['#]:[Completion rate]],'High-level overview'!I$9,FALSE)),"") -> JCU | J15: =IFERROR(IF(VLOOKUP(Table2[[#This Row],['#]],Table3[['#]:[Completion rate]],'High-level overview'!J$9,FALSE)=0,"",VLOOKUP(Table2[[#This Row],['#]],Table3[['#]:[Completion rate]],'High-level overview'!J$9,FALSE)),"") | K15: =IFERROR(IF(VLOOKUP(Table2[[#This Row],['#]],Table3[['#]:[Completion rate]],'High-level overview'!K$9,FALSE)=0,"",VLOOKUP(Table2[[#This Row],['#]],Table3[['#]:[Completion rate]],'High-level overview'!K$9,FALSE)),"") | ... M15: =IFERROR(IF(VLOOKUP(Table2[[#This Row],['#]],Table3[['#]:[Completion rate]],'High-level overview'!M$9,FALSE)=0,"",VLOOKUP(Table2[[#This Row],['#]],Table3[['#]:[Completion rate]],'High-level overview'!M$9,FALSE)),"")
C16: 5 | D16: =IFERROR(IF(VLOOKUP(Table2[[#This Row],['#]],Table3[['#]:[Completion rate]],'High-level overview'!D$9,FALSE)=0,"",VLOOKUP(Table2[[#This Row],['#]],Table3[['#]:[Completion rate]],'High-level overview'!D$9,FALSE)),"") -> Explore, implement and leverage Artificial Intelligence | E16: =IFERROR(IF(VLOOKUP(Table2[[#This Row],['#]],Table3[['#]:[Completion rate]],'High-level overview'!E$9,FALSE)=0,"",VLOOKUP(Table2[[#This Row],['#]],Table3[['#]:[Completion rate]],'High-level overview'!E$9,FALSE)),"") -> Finance | F16: =IFERROR(IF(VLOOKUP(Table2[[#This Row],['#]],Table3[['#]:[Completion rate]],'High-level overview'!F$9,FALSE)=0,"",VLOOKUP(Table2[[#This Row],['#]],Table3[['#]:[Completion rate]],'High-level overview'!F$9,FALSE)),"") -> Sales growth | G16: =IFERROR(IF(VLOOKUP(Table2[[#This Row],['#]],Table3[['#]:[Completion rate]],'High-level overview'!G$9,FALSE)=0,"",VLOOKUP(Table2[[#This Row],['#]],Table3[['#]:[Completion rate]],'High-level overview'!G$9,FALSE)),"") -> Service function | H16: =IFERROR(IF(VLOOKUP(Table2[[#This Row],['#]],Table3[['#]:[Completion rate]],'High-level overview'!H$9,FALSE)=0,"",VLOOKUP(Table2[[#This Row],['#]],Table3[['#]:[Completion rate]],'High-level overview'!H$9,FALSE)),"") -> Explore, implement and leverage Artificial Intelligence | I16: =IFERROR(IF(VLOOKUP(Table2[[#This Row],['#]],Table3[['#]:[Completion rate]],'High-level overview'!I$9,FALSE)=0,"",VLOOKUP(Table2[[#This Row],['#]],Table3[['#]:[Completion rate]],'High-level overview'!I$9,FALSE)),"") | J16: =IFERROR(IF(VLOOKUP(Table2[[#This Row],['#]],Table3[['#]:[Completion rate]],'High-level overview'!J$9,FALSE)=0,"",VLOOKUP(Table2[[#This Row],['#]],Table3[['#]:[Completion rate]],'High-level overview'!J$9,FALSE)),"") | K16: =IFERROR(IF(VLOOKUP(Table2[[#This Row],['#]],Table3[['#]:[Completion rate]],'High-level overview'!K$9,FALSE)=0,"",VLOOKUP(Table2[[#This Row],['#]],Table3[['#]:[Completion rate]],'High-level overview'!K$9,FALSE)),"") | ... M16: =IFERROR(IF(VLOOKUP(Table2[[#This Row],['#]],Table3[['#]:[Completion rate]],'High-level overview'!M$9,FALSE)=0,"",VLOOKUP(Table2[[#This Row],['#]],Table3[['#]:[Completion rate]],'High-level overview'!M$9,FALSE)),"")
C17: 6 | D17: =IFERROR(IF(VLOOKUP(Table2[[#This Row],['#]],Table3[['#]:[Completion rate]],'High-level overview'!D$9,FALSE)=0,"",VLOOKUP(Table2[[#This Row],['#]],Table3[['#]:[Completion rate]],'High-level overview'!D$9,FALSE)),"") -> Secure the voice of the customer through insights | E17: =IFERROR(IF(VLOOKUP(Table2[[#This Row],['#]],Table3[['#]:[Completion rate]],'High-level overview'!E$9,FALSE)=0,"",VLOOKUP(Table2[[#This Row],['#]],Table3[['#]:[Completion rate]],'High-level overview'!E$9,FALSE)),"") -> Finance | F17: =IFERROR(IF(VLOOKUP(Table2[[#This Row],['#]],Table3[['#]:[Completion rate]],'High-level overview'!F$9,FALSE)=0,"",VLOOKUP(Table2[[#This Row],['#]],Table3[['#]:[Completion rate]],'High-level overview'!F$9,FALSE)),"") -> Sales growth | G17: =IFERROR(IF(VLOOKUP(Table2[[#This Row],['#]],Table3[['#]:[Completion rate]],'High-level overview'!G$9,FALSE)=0,"",VLOOKUP(Table2[[#This Row],['#]],Table3[['#]:[Completion rate]],'High-level overview'!G$9,FALSE)),"") -> Service function | H17: =IFERROR(IF(VLOOKUP(Table2[[#This Row],['#]],Table3[['#]:[Completion rate]],'High-level overview'!H$9,FALSE)=0,"",VLOOKUP(Table2[[#This Row],['#]],Table3[['#]:[Completion rate]],'High-level overview'!H$9,FALSE)),"") -> Secure the voice of the customer through insights | I17: =IFERROR(IF(VLOOKUP(Table2[[#This Row],['#]],Table3[['#]:[Completion rate]],'High-level overview'!I$9,FALSE)=0,"",VLOOKUP(Table2[[#This Row],['#]],Table3[['#]:[Completion rate]],'High-level overview'!I$9,FALSE)),"") | J17: =IFERROR(IF(VLOOKUP(Table2[[#This Row],['#]],Table3[['#]:[Completion rate]],'High-level overview'!J$9,FALSE)=0,"",VLOOKUP(Table2[[#This Row],['#]],Table3[['#]:[Completion rate]],'High-level overview'!J$9,FALSE)),"") | K17: =IFERROR(IF(VLOOKUP(Table2[[#This Row],['#]],Table3[['#]:[Completion rate]],'High-level overview'!K$9,FALSE)=0,"",VLOOKUP(Table2[[#This Row],['#]],Table3[['#]:[Completion rate]],'High-level overview'!K$9,FALSE)),"") | ... M17: =IFERROR(IF(VLOOKUP(Table2[[#This Row],['#]],Table3[['#]:[Completion rate]],'High-level overview'!M$9,FALSE)=0,"",VLOOKUP(Table2[[#This Row],['#]],Table3[['#]:[Completion rate]],'High-level overview'!M$9,FALSE)),"")
C18: 7 | D18: =IFERROR(IF(VLOOKUP(Table2[[#This Row],['#]],Table3[['#]:[Completion rate]],'High-level overview'!D$9,FALSE)=0,"",VLOOKUP(Table2[[#This Row],['#]],Table3[['#]:[Completion rate]],'High-level overview'!D$9,FALSE)),"") -> Make JYSK more sustainable | E18: =IFERROR(IF(VLOOKUP(Table2[[#This Row],['#]],Table3[['#]:[Completion rate]],'High-level overview'!E$9,FALSE)=0,"",VLOOKUP(Table2[[#This Row],['#]],Table3[['#]:[Completion rate]],'High-level overview'!E$9,FALSE)),"") -> Finance | F18: =IFERROR(IF(VLOOKUP(Table2[[#This Row],['#]],Table3[['#]:[Completion rate]],'High-level overview'!F$9,FALSE)=0,"",VLOOKUP(Table2[[#This Row],['#]],Table3[['#]:[Completion rate]],'High-level overview'!F$9,FALSE)),"") -> Sales growth | G18: =IFERROR(IF(VLOOKUP(Table2[[#This Row],['#]],Table3[['#]:[Completion rate]],'High-level overview'!G$9,FALSE)=0,"",VLOOKUP(Table2[[#This Row],['#]],Table3[['#]:[Completion rate]],'High-level overview'!G$9,FALSE)),"") -> Service function | H18: =IFERROR(IF(VLOOKUP(Table2[[#This Row],['#]],Table3[['#]:[Completion rate]],'High-level overview'!H$9,FALSE)=0,"",VLOOKUP(Table2[[#This Row],['#]],Table3[['#]:[Completion rate]],'High-level overview'!H$9,FALSE)),"") -> Make JYSK more sustainable | I18: =IFERROR(IF(VLOOKUP(Table2[[#This Row],['#]],Table3[['#]:[Completion rate]],'High-level overview'!I$9,FALSE)=0,"",VLOOKUP(Table2[[#This Row],['#]],Table3[['#]:[Completion rate]],'High-level overview'!I$9,FALSE)),"") | J18: =IFERROR(IF(VLOOKUP(Table2[[#This Row],['#]],Table3[['#]:[Completion rate]],'High-level overview'!J$9,FALSE)=0,"",VLOOKUP(Table2[[#This Row],['#]],Table3[['#]:[Completion rate]],'High-level overview'!J$9,FALSE)),"") | K18: =IFERROR(IF(VLOOKUP(Table2[[#This Row],['#]],Table3[['#]:[Completion rate]],'High-level overview'!K$9,FALSE)=0,"",VLOOKUP(Table2[[#This Row],['#]],Table3[['#]:[Completion rate]],'High-level overview'!K$9,FALSE)),"") | ... M18: =IFERROR(IF(VLOOKUP(Table2[[#This Row],['#]],Table3[['#]:[Completion rate]],'High-level overview'!M$9,FALSE)=0,"",VLOOKUP(Table2[[#This Row],['#]],Table3[['#]:[Completion rate]],'High-level overview'!M$9,FALSE)),"")
C19: 8 | D19: =IFERROR(IF(VLOOKUP(Table2[[#This Row],['#]],Table3[['#]:[Completion rate]],'High-level overview'!D$9,FALSE)=0,"",VLOOKUP(Table2[[#This Row],['#]],Table3[['#]:[Completion rate]],'High-level overview'!D$9,FALSE)),"") -> Enhance benefits from RTM | E19: =IFERROR(IF(VLOOKUP(Table2[[#This Row],['#]],Table3[['#]:[Completion rate]],'High-level overview'!E$9,FALSE)=0,"",VLOOKUP(Table2[[#This Row],['#]],Table3[['#]:[Completion rate]],'High-level overview'!E$9,FALSE)),"") -> Finance | F19: =IFERROR(IF(VLOOKUP(Table2[[#This Row],['#]],Table3[['#]:[Completion rate]],'High-level overview'!F$9,FALSE)=0,"",VLOOKUP(Table2[[#This Row],['#]],Table3[['#]:[Completion rate]],'High-level overview'!F$9,FALSE)),"") -> Sales growth | G19: =IFERROR(IF(VLOOKUP(Table2[[#This Row],['#]],Table3[['#]:[Completion rate]],'High-level overview'!G$9,FALSE)=0,"",VLOOKUP(Table2[[#This Row],['#]],Table3[['#]:[Completion rate]],'High-level overview'!G$9,FALSE)),"") -> Service function | H19: =IFERROR(IF(VLOOKUP(Table2[[#This Row],['#]],Table3[['#]:[Completion rate]],'High-level overview'!H$9,FALSE)=0,"",VLOOKUP(Table2[[#This Row],['#]],Table3[['#]:[Completion rate]],'High-level overview'!H$9,FALSE)),"") -> Enhance benefits from RTM | I19: =IFERROR(IF(VLOOKUP(Table2[[#This Row],['#]],Table3[['#]:[Completion rate]],'High-level overview'!I$9,FALSE)=0,"",VLOOKUP(Table2[[#This Row],['#]],Table3[['#]:[Completion rate]],'High-level overview'!I$9,FALSE)),"") | J19: =IFERROR(IF(VLOOKUP(Table2[[#This Row],['#]],Table3[['#]:[Completion rate]],'High-level overview'!J$9,FALSE)=0,"",VLOOKUP(Table2[[#This Row],['#]],Table3[['#]:[Completion rate]],'High-level overview'!J$9,FALSE)),"") | K19: =IFERROR(IF(VLOOKUP(Table2[[#This Row],['#]],Table3[['#]:[Completion rate]],'High-level overview'!K$9,FALSE)=0,"",VLOOKUP(Table2[[#This Row],['#]],Table3[['#]:[Completion rate]],'High-level overview'!K$9,FALSE)),"") | ... M19: =IFERROR(IF(VLOOKUP(Table2[[#This Row],['#]],Table3[['#]:[Completion rate]],'High-level overview'!M$9,FALSE)=0,"",VLOOKUP(Table2[[#This Row],['#]],Table3[['#]:[Completion rate]],'High-level overview'!M$9,FALSE)),"")
C20: 9 | D20: =IFERROR(IF(VLOOKUP(Table2[[#This Row],['#]],Table3[['#]:[Completion rate]],'High-level overview'!D$9,FALSE)=0,"",VLOOKUP(Table2[[#This Row],['#]],Table3[['#]:[Completion rate]],'High-level overview'!D$9,FALSE)),"") -> Upgrade web shops to 3.0 | E20: =IFERROR(IF(VLOOKUP(Table2[[#This Row],['#]],Table3[['#]:[Completion rate]],'High-level overview'!E$9,FALSE)=0,"",VLOOKUP(Table2[[#This Row],['#]],Table3[['#]:[Completion rate]],'High-level overview'!E$9,FALSE)),"") -> Customer first | F20: =IFERROR(IF(VLOOKUP(Table2[[#This Row],['#]],Table3[['#]:[Completion rate]],'High-level overview'!F$9,FALSE)=0,"",VLOOKUP(Table2[[#This Row],['#]],Table3[['#]:[Completion rate]],'High-level overview'!F$9,FALSE)),"") -> Easy shopping | G20: =IFERROR(IF(VLOOKUP(Table2[[#This Row],['#]],Table3[['#]:[Completion rate]],'High-level overview'!G$9,FALSE)=0,"",VLOOKUP(Table2[[#This Row],['#]],Table3[['#]:[Completion rate]],'High-level overview'!G$9,FALSE)),"") -> Service function | H20: =IFERROR(IF(VLOOKUP(Table2[[#This Row],['#]],Table3[['#]:[Completion rate]],'High-level overview'!H$9,FALSE)=0,"",VLOOKUP(Table2[[#This Row],['#]],Table3[['#]:[Completion rate]],'High-level overview'!H$9,FALSE)),"") -> Upgrade web shops to 3.0 | I20: =IFERROR(IF(VLOOKUP(Table2[[#This Row],['#]],Table3[['#]:[Completion rate]],'High-level overview'!I$9,FALSE)=0,"",VLOOKUP(Table2[[#This Row],['#]],Table3[['#]:[Completion rate]],'High-level overview'!I$9,FALSE)),"") | J20: =IFERROR(IF(VLOOKUP(Table2[[#This Row],['#]],Table3[['#]:[Completion rate]],'High-level overview'!J$9,FALSE)=0,"",VLOOKUP(Table2[[#This Row],['#]],Table3[['#]:[Completion rate]],'High-level overview'!J$9,FALSE)),"") | K20: =IFERROR(IF(VLOOKUP(Table2[[#This Row],['#]],Table3[['#]:[Completion rate]],'High-level overview'!K$9,FALSE)=0,"",VLOOKUP(Table2[[#This Row],['#]],Table3[['#]:[Completion rate]],'High-level overview'!K$9,FALSE)),"") | ... M20: =IFERROR(IF(VLOOKUP(Table2[[#This Row],['#]],Table3[['#]:[Completion rate]],'High-level overview'!M$9,FALSE)=0,"",VLOOKUP(Table2[[#This Row],['#]],Table3[['#]:[Completion rate]],'High-level overview'!M$9,FALSE)),"")
C21: 10 | D21: =IFERROR(IF(VLOOKUP(Table2[[#This Row],['#]],Table3[['#]:[Completion rate]],'High-level overview'!D$9,FALSE)=0,"",VLOOKUP(Table2[[#This Row],['#]],Table3[['#]:[Completion rate]],'High-level overview'!D$9,FALSE)),"") -> Improve delivery stability and service | E21: =IFERROR(IF(VLOOKUP(Table2[[#This Row],['#]],Table3[['#]:[Completion rate]],'High-level overview'!E$9,FALSE)=0,"",VLOOKUP(Table2[[#This Row],['#]],Table3[['#]:[Completion rate]],'High-level overview'!E$9,FALSE)),"") -> Internal processes | F21: =IFERROR(IF(VLOOKUP(Table2[[#This Row],['#]],Table3[['#]:[Completion rate]],'High-level overview'!F$9,FALSE)=0,"",VLOOKUP(Table2[[#This Row],['#]],Table3[['#]:[Completion rate]],'High-level overview'!F$9,FALSE)),"") -> Balanced flow of goods | G21: =IFERROR(IF(VLOOKUP(Table2[[#This Row],['#]],Table3[['#]:[Completion rate]],'High-level overview'!G$9,FALSE)=0,"",VLOOKUP(Table2[[#This Row],['#]],Table3[['#]:[Completion rate]],'High-level overview'!G$9,FALSE)),"") -> Service function | H21: =IFERROR(IF(VLOOKUP(Table2[[#This Row],['#]],Table3[['#]:[Completion rate]],'High-level overview'!H$9,FALSE)=0,"",VLOOKUP(Table2[[#This Row],['#]],Table3[['#]:[Completion rate]],'High-level overview'!H$9,FALSE)),"") -> Improve delivery stability and service | I21: =IFERROR(IF(VLOOKUP(Table2[[#This Row],['#]],Table3[['#]:[Completion rate]],'High-level overview'!I$9,FALSE)=0,"",VLOOKUP(Table2[[#This Row],['#]],Table3[['#]:[Completion rate]],'High-level overview'!I$9,FALSE)),"") | J21: =IFERROR(IF(VLOOKUP(Table2[[#This Row],['#]],Table3[['#]:[Completion rate]],'High-level overview'!J$9,FALSE)=0,"",VLOOKUP(Table2[[#This Row],['#]],Table3[['#]:[Completion rate]],'High-level overview'!J$9,FALSE)),"") | K21: =IFERROR(IF(VLOOKUP(Table2[[#This Row],['#]],Table3[['#]:[Completion rate]],'High-level overview'!K$9,FALSE)=0,"",VLOOKUP(Table2[[#This Row],['#]],Table3[['#]:[Completion rate]],'High-level overview'!K$9,FALSE)),"") | ... M21: =IFERROR(IF(VLOOKUP(Table2[[#This Row],['#]],Table3[['#]:[Completion rate]],'High-level overview'!M$9,FALSE)=0,"",VLOOKUP(Table2[[#This Row],['#]],Table3[['#]:[Completion rate]],'High-level overview'!M$9,FALSE)),"")
C22: 11 | D22: =IFERROR(IF(VLOOKUP(Table2[[#This Row],['#]],Table3[['#]:[Completion rate]],'High-level overview'!D$9,FALSE)=0,"",VLOOKUP(Table2[[#This Row],['#]],Table3[['#]:[Completion rate]],'High-level overview'!D$9,FALSE)),"") -> Simplify communication to stores | E22: =IFERROR(IF(VLOOKUP(Table2[[#This Row],['#]],Table3[['#]:[Completion rate]],'High-level overview'!E$9,FALSE)=0,"",VLOOKUP(Table2[[#This Row],['#]],Table3[['#]:[Completion rate]],'High-level overview'!E$9,FALSE)),"") -> Internal processes | F22: =IFERROR(IF(VLOOKUP(Table2[[#This Row],['#]],Table3[['#]:[Completion rate]],'High-level overview'!F$9,FALSE)=0,"",VLOOKUP(Table2[[#This Row],['#]],Table3[['#]:[Completion rate]],'High-level overview'!F$9,FALSE)),"") -> Attractive stores | G22: =IFERROR(IF(VLOOKUP(Table2[[#This Row],['#]],Table3[['#]:[Completion rate]],'High-level overview'!G$9,FALSE)=0,"",VLOOKUP(Table2[[#This Row],['#]],Table3[['#]:[Completion rate]],'High-level overview'!G$9,FALSE)),"") -> Service function | H22: =IFERROR(IF(VLOOKUP(Table2[[#This Row],['#]],Table3[['#]:[Completion rate]],'High-level overview'!H$9,FALSE)=0,"",VLOOKUP(Table2[[#This Row],['#]],Table3[['#]:[Completion rate]],'High-level overview'!H$9,FALSE)),"") -> Simplify communication to stores | I22: =IFERROR(IF(VLOOKUP(Table2[[#This Row],['#]],Table3[['#]:[Completion rate]],'High-level overview'!I$9,FALSE)=0,"",VLOOKUP(Table2[[#This Row],['#]],Table3[['#]:[Completion rate]],'High-level overview'!I$9,FALSE)),"") | J22: =IFERROR(IF(VLOOKUP(Table2[[#This Row],['#]],Table3[['#]:[Completion rate]],'High-level overview'!J$9,FALSE)=0,"",VLOOKUP(Table2[[#This Row],['#]],Table3[['#]:[Completion rate]],'High-level overview'!J$9,FALSE)),"") | K22: =IFERROR(IF(VLOOKUP(Table2[[#This Row],['#]],Table3[['#]:[Completion rate]],'High-level overview'!K$9,FALSE)=0,"",VLOOKUP(Table2[[#This Row],['#]],Table3[['#]:[Completion rate]],'High-level overview'!K$9,FALSE)),"") | ... M22: =IFERROR(IF(VLOOKUP(Table2[[#This Row],['#]],Table3[['#]:[Completion rate]],'High-level overview'!M$9,FALSE)=0,"",VLOOKUP(Table2[[#This Row],['#]],Table3[['#]:[Completion rate]],'High-level overview'!M$9,FALSE)),"")
C23: 12 | D23: =IFERROR(IF(VLOOKUP(Table2[[#This Row],['#]],Table3[['#]:[Completion rate]],'High-level overview'!D$9,FALSE)=0,"",VLOOKUP(Table2[[#This Row],['#]],Table3[['#]:[Completion rate]],'High-level overview'!D$9,FALSE)),"") -> Improve situation-based marketing and branding | E23: =IFERROR(IF(VLOOKUP(Table2[[#This Row],['#]],Table3[['#]:[Completion rate]],'High-level overview'!E$9,FALSE)=0,"",VLOOKUP(Table2[[#This Row],['#]],Table3[['#]:[Completion rate]],'High-level overview'!E$9,FALSE)),"") -> Internal processes | F23: =IFERROR(IF(VLOOKUP(Table2[[#This Row],['#]],Table3[['#]:[Completion rate]],'High-level overview'!F$9,FALSE)=0,"",VLOOKUP(Table2[[#This Row],['#]],Table3[['#]:[Completion rate]],'High-level overview'!F$9,FALSE)),"") -> Effective marketing | G23: =IFERROR(IF(VLOOKUP(Table2[[#This Row],['#]],Table3[['#]:[Completion rate]],'High-level overview'!G$9,FALSE)=0,"",VLOOKUP(Table2[[#This Row],['#]],Table3[['#]:[Completion rate]],'High-level overview'!G$9,FALSE)),"") -> Service function | H23: =IFERROR(IF(VLOOKUP(Table2[[#This Row],['#]],Table3[['#]:[Completion rate]],'High-level overview'!H$9,FALSE)=0,"",VLOOKUP(Table2[[#This Row],['#]],Table3[['#]:[Completion rate]],'High-level overview'!H$9,FALSE)),"") -> Improve situation-based marketing and branding | I23: =IFERROR(IF(VLOOKUP(Table2[[#This Row],['#]],Table3[['#]:[Completion rate]],'High-level overview'!I$9,FALSE)=0,"",VLOOKUP(Table2[[#This Row],['#]],Table3[['#]:[Completion rate]],'High-level overview'!I$9,FALSE)),"") | J23: =IFERROR(IF(VLOOKUP(Table2[[#This Row],['#]],Table3[['#]:[Completion rate]],'High-level overview'!J$9,FALSE)=0,"",VLOOKUP(Table2[[#This Row],['#]],Table3[['#]:[Completion rate]],'High-level overview'!J$9,FALSE)),"") | K23: =IFERROR(IF(VLOOKUP(Table2[[#This Row],['#]],Table3[['#]:[Completion rate]],'High-level overview'!K$9,FALSE)=0,"",VLOOKUP(Table2[[#This Row],['#]],Table3[['#]:[Completion rate]],'High-level overview'!K$9,FALSE)),"") | ... M23: =IFERROR(IF(VLOOKUP(Table2[[#This Row],['#]],Table3[['#]:[Completion rate]],'High-level overview'!M$9,FALSE)=0,"",VLOOKUP(Table2[[#This Row],['#]],Table3[['#]:[Completion rate]],'High-level overview'!M$9,FALSE)),"")
... C51: 40 | D51: =IFERROR(IF(VLOOKUP(Table2[[#This Row],['#]],Table3[['#]:[Completion rate]],'High-level overview'!D$9,FALSE)=0,"",VLOOKUP(Table2[[#This Row],['#]],Table3[['#]:[Completion rate]],'High-level overview'!D$9,FALSE)),"") | E51: =IFERROR(IF(VLOOKUP(Table2[[#This Row],['#]],Table3[['#]:[Completion rate]],'High-level overview'!E$9,FALSE)=0,"",VLOOKUP(Table2[[#This Row],['#]],Table3[['#]:[Completion rate]],'High-level overview'!E$9,FALSE)),"") | F51: =IFERROR(IF(VLOOKUP(Table2[[#This Row],['#]],Table3[['#]:[Completion rate]],'High-level overview'!F$9,FALSE)=0,"",VLOOKUP(Table2[[#This Row],['#]],Table3[['#]:[Completion rate]],'High-level overview'!F$9,FALSE)),"") | G51: =IFERROR(IF(VLOOKUP(Table2[[#This Row],['#]],Table3[['#]:[Completion rate]],'High-level overview'!G$9,FALSE)=0,"",VLOOKUP(Table2[[#This Row],['#]],Table3[['#]:[Completion rate]],'High-level overview'!G$9,FALSE)),"") | H51: =IFERROR(IF(VLOOKUP(Table2[[#This Row],['#]],Table3[['#]:[Completion rate]],'High-level overview'!H$9,FALSE)=0,"",VLOOKUP(Table2[[#This Row],['#]],Table3[['#]:[Completion rate]],'High-level overview'!H$9,FALSE)),"") | I51: =IFERROR(IF(VLOOKUP(Table2[[#This Row],['#]],Table3[['#]:[Completion rate]],'High-level overview'!I$9,FALSE)=0,"",VLOOKUP(Table2[[#This Row],['#]],Table3[['#]:[Completion rate]],'High-level overview'!I$9,FALSE)),"") | J51: =IFERROR(IF(VLOOKUP(Table2[[#This Row],['#]],Table3[['#]:[Completion rate]],'High-level overview'!J$9,FALSE)=0,"",VLOOKUP(Table2[[#This Row],['#]],Table3[['#]:[Completion rate]],'High-level overview'!J$9,FALSE)),"") | K51: =IFERROR(IF(VLOOKUP(Table2[[#This Row],['#]],Table3[['#]:[Completion rate]],'High-level overview'!K$9,FALSE)=0,"",VLOOKUP(Table2[[#This Row],['#]],Table3[['#]:[Completion rate]],'High-level overview'!K$9,FALSE)),"") | ... M51: =IFERROR(IF(VLOOKUP(Table2[[#This Row],['#]],Table3[['#]:[Completion rate]],'High-level overview'!M$9,FALSE)=0,"",VLOOKUP(Table2[[#This Row],['#]],Table3[['#]:[Completion rate]],'High-level overview'!M$9,FALSE)),"")

Sheet Quick guide
A1: Quick guide
A2: Excel sheet:

Sheet Backend
O1: Completion rate
B2: Type of CSF | D2: Perspective | F2: Focus Area | I2: Finance | J2: Customer first | K2: Internal processes | L2: Employees & learning | O2: 1
B3: JYSK | D3: Finance | F3: Even better cost management | I3: Even better cost management | J3: Reliable product quality | K3: Balanced flow of goods | L3: Strong talent pipeline | M3: Even better cost management | O3: 0.75
B4: Service Function | D4: Customer first | F4: Improve earnings | I4: Improve earnings | J4: Easy shopping | K4: Relevant assortment | L4: Relevant training | M4: Improve earnings | O4: 0.5
B5: Local | D5: Internal processes | F5: Sales growth | I5: Sales growth | J5: Competent service | K5: Attractive stores | L5: Great store management | M5: Sales growth | O5: 0.25
D6: Employees & learning | F6: Expansion | I6: Expansion | J6: Seamless cross channel | K6: Effective marketing | L6: Attractive place to work | M6: Expansion | O6: Not started
F7: Reliable product quality | M7: Reliable product quality | O7: Not relevant
F8: Easy shopping | M8: Easy shopping
F9: Competent service | M9: Competent service
F10: Seamless cross channel | I10: RGB | M10: Seamless cross channel
F11: Balanced flow of goods | I11: 252 | J11: 197 | K11: 176 | L11: 223 | M11: Balanced flow of goods
F12: Relevant assortment | I12: 209 | J12: 222 | K12: 203 | L12: 142 | M12: Relevant assortment
F13: Attractive stores | I13: 99 | J13: 239 | K13: 169 | L13: 120 | M13: Attractive stores
F14: Effective marketing | M14: Effective marketing
F15: Strong talent pipeline | M15: Strong talent pipeline
F16: Relevant training | M16: Relevant training
F17: Great store management | M17: Great store management
F18: Attractive place to work | M18: Attractive place to work
I23: Formulas for conditional formatting of perspectives
I24: =OR(AND($D10="Finance",$E10="Even better cost management"),AND($D10="Finance",$E10="Improve earnings"),AND($D10="Finance",$E10="Sales Growth"),AND($D10="Finance",$E10="Expansion")) -> FALSE
I25: =OR(AND($D10="Customer first",$E10="Reliable product quality"),AND($D10="Customer first",$E10="Easy shopping"),AND($D10="Customer first",$E10="Competent service"),AND($D10="Customer first",$E10="Seamless cross channel")) -> FALSE
I26: =OR(AND($D10="Internal processes",$E10="Balanced flow of goods"),AND($D10="Internal processes",$E10="Relevant assortment"),AND($D10="Internal processes",$E10="Attractive stores"),AND($D10="Internal processes",$E10="Effective marketing")) -> FALSE
I27: =OR(AND($D10="Employees & learning",$E10="Strong talent pipeline"),AND($D10="Employees & learning",$E10="Relevant training"),AND($D10="Employees & learning",$E10="Great store management"),AND($D10="Employees & learning",$E10="Attractive place to work")) -> FALSE
